dmm.py
dmm_search-1.1.0.dist-info/DESCRIPTION.rst
dmm_search-1.1.0.dist-info/METADATA
dmm_search-1.1.0.dist-info/metadata.json
dmm_search-1.1.0.dist-info/RECORD
dmm_search-1.1.0.dist-info/top_level.txt
dmm_search-1.1.0.dist-info/WHEEL
