Metadata-Version: 2.0
Name: dmm-search
Version: 1.1.0
Summary: DMM search API for Python
Home-page: https://github.com/otknoy/dmm_search
Author: otknoy
Author-email: otknoy@gmail.com
License: UNKNOWN
Keywords: dmm,search,api
Platform: UNKNOWN
Requires-Dist: requests
